{"title":"Limited to 111.8 days old","region":"hitchin_johnsonpl","updated_on":"2024-03-28T10:24:59Z","next_on":"2024-03-29T09:31:51Z","searches":[{"name":"johnsonpl","url_r":"https://www.rightmove.co.uk/property-for-sale/find.html?locationIdentifier=POSTCODE^3880044&radius=0.25&maxPrice=400000&sortType=6&channel=BUY&includeSSTC=true&dontShow=retirement,sharedOwnership","url_z":"https://www.zoopla.co.uk/for-sale/property/sg4-9fj/?radius=0.25&q=SG4+9FJ&search_source=for-sale&beds_min=2&results_sort=newest_listings&is_auction=false&is_retirement_home=false&is_shared_ownership=false&include_sold=true&price_max=400000","url_o":"https://www.onthemarket.com/for-sale/property/sg4-9fj/?view=map&radius=0.25&auction=false&retirement=false&shared-ownership=false&under-offer=false&max-price=400000"}],"items":[{"id":"146189234","channel":"buy","price":400000.0,"date_added":"2024-03-27T10:47:03Z","address":"Dacre Road, Hitchin","address_postcode":"SG5 1QL","bedrooms":2,"bathrooms":1,"property_group":"Houses","property_group_icon":"🏡","key_features":["Council Tax Band: B"],"coordinates":[51.953733,-0.267808],"closest":{"place":"HIT station","miles":0.118,"coords":[51.953323,-0.265135]},"images":[{"url":"https://media.rightmove.co.uk/dir/8k/7677/146189234/7677_27338308_IMG_00_0000_max_656x437.jpeg"},{"url":"https://media.rightmove.co.uk/dir/8k/7677/146189234/7677_27338308_IMG_02_0000_max_656x437.jpeg"},{"url":"https://media.rightmove.co.uk/dir/8k/7677/146189234/7677_27338308_IMG_03_0000_max_656x437.jpeg"},{"url":"https://media.rightmove.co.uk/dir/8k/7677/146189234/7677_27338308_IMG_04_0000_max_656x437.jpeg"},{"url":"https://media.rightmove.co.uk/dir/8k/7677/146189234/7677_27338308_IMG_05_0000_max_656x437.jpeg"},{"url":"https://media.rightmove.co.uk/dir/8k/7677/146189234/7677_27338308_IMG_06_0000_max_656x437.jpeg"},{"url":"https://media.rightmove.co.uk/dir/8k/7677/146189234/7677_27338308_IMG_07_0000_max_656x437.jpeg"},{"url":"https://media.rightmove.co.uk/dir/8k/7677/146189234/7677_27338308_IMG_08_0000_max_656x437.jpeg"},{"url":"https://media.rightmove.co.uk/dir/8k/7677/146189234/7677_27338308_IMG_09_0000_max_656x437.jpeg"},{"url":"https://media.rightmove.co.uk/dir/8k/7677/146189234/7677_27338308_IMG_10_0000_max_656x437.jpeg"},{"url":"https://media.rightmove.co.uk/dir/8k/7677/146189234/7677_27338308_IMG_11_0000_max_656x437.jpeg"},{"url":"https://media.rightmove.co.uk/dir/8k/7677/146189234/7677_27338308_IMG_12_0000_max_656x437.jpeg"}],"floorplans":[{"url":"https://media.rightmove.co.uk/8k/7677/146189234/7677_27338308_FLP_00_0000.jpeg","caption":"Floorplan 1"}],"brochures":[{"url":"https://docs.rezi.cloud/KkwbeO%2bo005%2fdF7uqrLDxiQKyt1crcQkviDW5oz%2fMhY%3d/41079873.pdf?v=000000000c7a7e7a","caption":"Brochure 1"}],"epcs":[{"url":"https://media.rightmove.co.uk/8k/7677/146189234/7677_27338308_EPCGRAPH_00_0000.png","caption":"EPC 1"}],"agency":{"url":"https://media.rightmove.co.uk/brand/brand_logo_56245_0006.png","caption":"Country Properties, Hitchin"},"summary":"A delightful two bedroom cottage located on the highly desirable Dacre Road, providing easy access to the town centre and station.This fine home is presented in superb condition throughout with a bright open plan living/dining room which opens into a fitted galley kitchen, utility area ...","is_new":false},{"id":"146022530","channel":"buy","price":235000.0,"date_added":"2024-03-21T20:07:03Z","address":"45 Walsworth Road, Hitchin","address_postcode":"SG4 9SU","bedrooms":1,"bathrooms":1,"property_group":"Flats / Apartments","property_group_icon":"🏢","key_features":["FREEHOLD","Council Tax Band: A"],"coordinates":[51.951709,-0.268079],"closest":{"place":"HIT station","miles":0.168,"coords":[51.953323,-0.265135]},"images":[{"url":"https://media.rightmove.co.uk/dir/94k/93881/146022530/93881_BNJ_HB_LFSYCL_518_710309734_IMG_00_0000_max_656x437.jpeg"},{"url":"https://media.rightmove.co.uk/dir/94k/93881/146022530/93881_BNJ_HB_LFSYCL_518_710309734_IMG_01_0000_max_656x437.jpeg"},{"url":"https://media.rightmove.co.uk/dir/94k/93881/146022530/93881_BNJ_HB_LFSYCL_518_710309734_IMG_02_0000_max_656x437.jpeg"},{"url":"https://media.rightmove.co.uk/dir/94k/93881/146022530/93881_BNJ_HB_LFSYCL_518_710309734_IMG_03_0000_max_656x437.jpeg"},{"url":"https://media.rightmove.co.uk/dir/94k/93881/146022530/93881_BNJ_HB_LFSYCL_518_710309734_IMG_04_0000_max_656x437.jpeg"},{"url":"https://media.rightmove.co.uk/dir/94k/93881/146022530/93881_BNJ_HB_LFSYCL_518_710309734_IMG_05_0000_max_656x437.jpeg"},{"url":"https://media.rightmove.co.uk/dir/94k/93881/146022530/93881_BNJ_HB_LFSYCL_518_710309734_IMG_06_0000_max_656x437.jpeg"},{"url":"https://media.rightmove.co.uk/dir/94k/93881/146022530/93881_BNJ_HB_LFSYCL_518_710309734_IMG_07_0000_max_656x437.jpeg"},{"url":"https://media.rightmove.co.uk/dir/94k/93881/146022530/93881_BNJ_HB_LFSYCL_518_710309734_IMG_08_0000_max_656x437.jpeg"}],"floorplans":[{"url":"https://media.rightmove.co.uk/94k/93881/146022530/93881_BNJ_HB_LFSYCL_518_710309734_FLP_00_0000.jpeg","caption":"Floorplan 1"}],"agency":{"url":"https://media.rightmove.co.uk/company/clogo_35489_0006.png","caption":"Benjamin Stevens, Edgware"},"summary":"Offered chain free to investors only, this one bedroom apartment is conveniently located between the Railway Station & Town Centre in the highly sought after Market Town of Hitchin","is_new":false,"zoopla_advert_id":66933794},{"id":"145925780","channel":"buy","price":300000.0,"date_added":"2024-03-19T22:01:04Z","address_street_num":"92 Johnson Place, 65","address":"Walsworth Road, Hitchin","address_postcode":"SG4 9FJ","bedrooms":2,"bathrooms":2,"size_sqm":63.5,"property_group":"Flats / Apartments","property_group_icon":"🏢","sold_let":"Sold STC","key_features":["Penthouse apartment on top floor","Allocated private parking in secure underground car park","LEASEHOLD","Years left: 198","Ground Rent: 1.0","Service charge: 1882.0","Council Tax Band: C"],"coordinates":[51.953033,-0.265988],"closest":{"place":"HIT station","miles":0.042,"coords":[51.953323,-0.265135]},"images":[{"url":"https://media.rightmove.co.uk/dir/240k/239360/145925780/239360_baf58768-e045-42c4-92d2-324aec52bd93_IMG_00_0000_max_656x437.jpeg"},{"url":"https://media.rightmove.co.uk/dir/240k/239360/145925780/239360_baf58768-e045-42c4-92d2-324aec52bd93_IMG_01_0000_max_656x437.jpeg"},{"url":"https://media.rightmove.co.uk/dir/240k/239360/145925780/239360_baf58768-e045-42c4-92d2-324aec52bd93_IMG_02_0000_max_656x437.jpeg"},{"url":"https://media.rightmove.co.uk/dir/240k/239360/145925780/239360_baf58768-e045-42c4-92d2-324aec52bd93_IMG_03_0000_max_656x437.jpeg"},{"url":"https://media.rightmove.co.uk/dir/240k/239360/145925780/239360_baf58768-e045-42c4-92d2-324aec52bd93_IMG_04_0000_max_656x437.jpeg"},{"url":"https://media.rightmove.co.uk/dir/240k/239360/145925780/239360_baf58768-e045-42c4-92d2-324aec52bd93_IMG_05_0000_max_656x437.jpeg"},{"url":"https://media.rightmove.co.uk/dir/240k/239360/145925780/239360_baf58768-e045-42c4-92d2-324aec52bd93_IMG_06_0000_max_656x437.jpeg"},{"url":"https://media.rightmove.co.uk/dir/240k/239360/145925780/239360_baf58768-e045-42c4-92d2-324aec52bd93_IMG_07_0000_max_656x437.jpeg"},{"url":"https://media.rightmove.co.uk/dir/240k/239360/145925780/239360_baf58768-e045-42c4-92d2-324aec52bd93_IMG_08_0000_max_656x437.jpeg"},{"url":"https://media.rightmove.co.uk/dir/240k/239360/145925780/239360_baf58768-e045-42c4-92d2-324aec52bd93_IMG_09_0000_max_656x437.jpeg"},{"url":"https://media.rightmove.co.uk/dir/240k/239360/145925780/239360_baf58768-e045-42c4-92d2-324aec52bd93_IMG_10_0000_max_656x437.jpeg"},{"url":"https://media.rightmove.co.uk/dir/240k/239360/145925780/239360_baf58768-e045-42c4-92d2-324aec52bd93_IMG_11_0000_max_656x437.jpeg"},{"url":"https://media.rightmove.co.uk/dir/240k/239360/145925780/239360_baf58768-e045-42c4-92d2-324aec52bd93_IMG_12_0000_max_656x437.jpeg"},{"url":"https://media.rightmove.co.uk/dir/240k/239360/145925780/239360_baf58768-e045-42c4-92d2-324aec52bd93_IMG_13_0000_max_656x437.jpeg"}],"floorplans":[{"url":"https://media.rightmove.co.uk/240k/239360/145925780/239360_baf58768-e045-42c4-92d2-324aec52bd93_FLP_00_0000.jpeg","caption":"Floorplan 1"}],"agency":{"url":"https://media.rightmove.co.uk/brand/brand_logo_90119_0000.jpeg","caption":"Wellington Evans, Hitchin"},"summary":"Located in an unrivalled position, directly opposite Hitchin mainline train station, this exceptional penthouse apartment offers a combination of luxury and convenience. Boasting an extended lease with a peppercorn ground rent, this well presented two-bedroom property epitomises modern urban living.","is_new":false,"zoopla_uprn":10023319059,"zoopla_advert_id":66909835,"zoopla_est":289.0,"zoopla_estimate_date":"2024-03-11T14:48:32.720000Z","zoopla_peak":316.0,"zoopla_peak_date":"Dec 2022","zoopla_rent_estimate":1450.0},{"id":"145198979","channel":"buy","price":230000.0,"date_added":"2024-02-28T12:00:07Z","address_street_num":"87","address":"Cooks Way, Hitchin","address_postcode":"SG4 0JG","bedrooms":2,"bathrooms":1,"property_group":"Flats / Apartments","property_group_icon":"🏢","sold_let":"Sold STC","key_features":["LEASEHOLD","Years left: 183"],"coordinates":[51.95524,-0.26476],"closest":{"place":"HIT station","miles":0.134,"coords":[51.953323,-0.265135]},"images":[{"url":"https://media.rightmove.co.uk/dir/1k/436/145198979/436_BHI230050_IMG_00_0000_max_656x437.jpeg","caption":"Front Aspect"},{"url":"https://media.rightmove.co.uk/dir/1k/436/145198979/436_BHI230050_IMG_01_0000_max_656x437.jpeg","caption":"Living Room"},{"url":"https://media.rightmove.co.uk/dir/1k/436/145198979/436_BHI230050_IMG_02_0000_max_656x437.jpeg","caption":"Living Room"},{"url":"https://media.rightmove.co.uk/dir/1k/436/145198979/436_BHI230050_IMG_03_0000_max_656x437.jpeg","caption":"Living/Kitchen"},{"url":"https://media.rightmove.co.uk/dir/1k/436/145198979/436_BHI230050_IMG_04_0000_max_656x437.jpeg","caption":"Living/Kitchen"},{"url":"https://media.rightmove.co.uk/dir/1k/436/145198979/436_BHI230050_IMG_05_0000_max_656x437.jpeg","caption":"Living/Kitchen"},{"url":"https://media.rightmove.co.uk/dir/1k/436/145198979/436_BHI230050_IMG_06_0000_max_656x437.jpeg","caption":"Kitchen"},{"url":"https://media.rightmove.co.uk/dir/1k/436/145198979/436_BHI230050_IMG_07_0000_max_656x437.jpeg","caption":"Hallway"},{"url":"https://media.rightmove.co.uk/dir/1k/436/145198979/436_BHI230050_IMG_08_0000_max_656x437.jpeg","caption":"Bed Two"},{"url":"https://media.rightmove.co.uk/dir/1k/436/145198979/436_BHI230050_IMG_09_0000_max_656x437.jpeg","caption":"Bed Two"},{"url":"https://media.rightmove.co.uk/dir/1k/436/145198979/436_BHI230050_IMG_10_0000_max_656x437.jpeg","caption":"Bed One"},{"url":"https://media.rightmove.co.uk/dir/1k/436/145198979/436_BHI230050_IMG_11_0000_max_656x437.jpeg","caption":"PHOTOGRAPHY"},{"url":"https://media.rightmove.co.uk/dir/1k/436/145198979/436_BHI230050_IMG_12_0000_max_656x437.jpeg","caption":"Balcony"},{"url":"https://media.rightmove.co.uk/dir/1k/436/145198979/436_BHI230050_IMG_13_0000_max_656x437.jpeg","caption":"Front Aspect"},{"url":"https://media.rightmove.co.uk/dir/1k/436/145198979/436_BHI230050_IMG_14_0000_max_656x437.jpeg","caption":"Front Aspect"}],"floorplans":[{"url":"https://media.rightmove.co.uk/1k/436/145198979/436_BHI230050_FLP_00_0000.jpeg","caption":"FLOOR-PLAN"}],"epcs":[{"url":"https://media.rightmove.co.uk/1k/436/145198979/436_BHI230050_EPCGRAPH_00_0000.png","caption":"EPC Rating Graph"}],"agency":{"url":"https://media.rightmove.co.uk/brand/brand_logo_25_0004.png","caption":"Taylors Estate Agents, Hitchin"},"summary":"A well-presented two bedroom apartment which comes with a balcony, allocated parking and is conveniently placed for Hitchin train station and town centre. The property is being sold on a CHAIN FREE basis and comprises of a spacious living room with French doors leading onto a generous ...","is_new":false,"zoopla_uprn":10013801748,"zoopla_advert_id":66746242,"zoopla_est":234.0,"zoopla_estimate_date":"2024-03-11T14:48:32.720000Z","zoopla_peak":273.0,"zoopla_peak_date":"Jul 2022","zoopla_rent_estimate":1200.0},{"id":"144599483","channel":"buy","price":365000.0,"date_added":"2024-02-10T15:49:02Z","address_street_num":"3","address":"Cooks Way, Hitchin","address_postcode":"SG4 0JL","bedrooms":2,"bathrooms":1,"property_group":"Houses","property_group_icon":"🏡","key_features":["Council Tax Band: C"],"coordinates":[51.956123,-0.26419],"closest":{"place":"HIT station","miles":0.198,"coords":[51.953323,-0.265135]},"images":[{"url":"https://media.rightmove.co.uk/dir/16k/15848/144599483/15848_27241733_IMG_00_0000_max_656x437.jpeg"},{"url":"https://media.rightmove.co.uk/dir/16k/15848/144599483/15848_27241733_IMG_01_0000_max_656x437.jpeg"},{"url":"https://media.rightmove.co.uk/dir/16k/15848/144599483/15848_27241733_IMG_02_0000_max_656x437.jpeg"},{"url":"https://media.rightmove.co.uk/dir/16k/15848/144599483/15848_27241733_IMG_03_0000_max_656x437.jpeg"},{"url":"https://media.rightmove.co.uk/dir/16k/15848/144599483/15848_27241733_IMG_04_0000_max_656x437.jpeg"},{"url":"https://media.rightmove.co.uk/dir/16k/15848/144599483/15848_27241733_IMG_05_0000_max_656x437.jpeg"},{"url":"https://media.rightmove.co.uk/dir/16k/15848/144599483/15848_27241733_IMG_06_0000_max_656x437.jpeg"},{"url":"https://media.rightmove.co.uk/dir/16k/15848/144599483/15848_27241733_IMG_07_0000_max_656x437.jpeg"},{"url":"https://media.rightmove.co.uk/dir/16k/15848/144599483/15848_27241733_IMG_08_0000_max_656x437.jpeg"},{"url":"https://media.rightmove.co.uk/dir/16k/15848/144599483/15848_27241733_IMG_09_0000_max_656x437.jpeg"},{"url":"https://media.rightmove.co.uk/dir/16k/15848/144599483/15848_27241733_IMG_10_0000_max_656x437.jpeg"},{"url":"https://media.rightmove.co.uk/dir/16k/15848/144599483/15848_27241733_IMG_11_0000_max_656x437.jpeg"},{"url":"https://media.rightmove.co.uk/dir/16k/15848/144599483/15848_27241733_IMG_12_0000_max_656x437.jpeg"},{"url":"https://media.rightmove.co.uk/dir/16k/15848/144599483/15848_27241733_IMG_13_0000_max_656x437.jpeg"}],"floorplans":[{"url":"https://media.rightmove.co.uk/16k/15848/144599483/15848_27241733_FLP_00_0000.jpeg","caption":"Floorplan 1"}],"brochures":[{"url":"https://docs.rezi.cloud/6%2fnI0puUXtqRHDG8tGib3IagiMGZg89Y2zCBhDvT%2bmg%3d/40436812.pdf?v=0000000001de00ad","caption":"Brochure 1"}],"epcs":[{"url":"https://media.rightmove.co.uk/16k/15848/144599483/15848_27241733_EPCGRAPH_00_0000.png","caption":"EPC 1"}],"agency":{"url":"https://media.rightmove.co.uk/16k/15848/branch_logo_15848_0006.png","caption":"Stonegate Estates, Hitchin"},"summary":"A two double bedroom mid terrace property situated within walking distance of the train station and the town centre. Parking spaces to rear. Enclosed rear garden.Ideal first time buy or investment purchase.","is_new":false,"zoopla_uprn":10023326624,"zoopla_advert_id":66615799,"zoopla_est":360.0,"zoopla_estimate_date":"2024-03-11T14:48:32.720000Z","zoopla_peak":398.0,"zoopla_peak_date":"May 2022"},{"id":"144476300","channel":"buy","price":270000.0,"date_added":"2024-02-07T16:52:04Z","address_street_num":"43","address":"Walsworth Road, Hitchin","address_postcode":"SG4 9SY","bedrooms":2,"bathrooms":2,"property_group":"Flats / Apartments","property_group_icon":"🏢","key_features":["Second floor accommodation","Allocated underground car parking","LEASEHOLD","Council Tax Band: B"],"coordinates":[51.952137,-0.266587],"closest":{"place":"HIT station","miles":0.103,"coords":[51.953323,-0.265135]},"images":[{"url":"https://media.rightmove.co.uk/dir/8k/7677/144476300/7677_26391003_IMG_00_0000_max_656x437.jpeg"},{"url":"https://media.rightmove.co.uk/dir/8k/7677/144476300/7677_26391003_IMG_01_0000_max_656x437.jpeg"},{"url":"https://media.rightmove.co.uk/dir/8k/7677/144476300/7677_26391003_IMG_02_0000_max_656x437.jpeg"},{"url":"https://media.rightmove.co.uk/dir/8k/7677/144476300/7677_26391003_IMG_03_0000_max_656x437.jpeg"},{"url":"https://media.rightmove.co.uk/dir/8k/7677/144476300/7677_26391003_IMG_04_0000_max_656x437.jpeg"},{"url":"https://media.rightmove.co.uk/dir/8k/7677/144476300/7677_26391003_IMG_05_0000_max_656x437.jpeg"},{"url":"https://media.rightmove.co.uk/dir/8k/7677/144476300/7677_26391003_IMG_06_0000_max_656x437.jpeg"},{"url":"https://media.rightmove.co.uk/dir/8k/7677/144476300/7677_26391003_IMG_07_0000_max_656x437.jpeg"},{"url":"https://media.rightmove.co.uk/dir/8k/7677/144476300/7677_26391003_IMG_08_0000_max_656x437.jpeg"},{"url":"https://media.rightmove.co.uk/dir/8k/7677/144476300/7677_26391003_IMG_09_0000_max_656x437.jpeg"}],"floorplans":[{"url":"https://media.rightmove.co.uk/8k/7677/144476300/7677_26391003_FLP_00_0000.jpeg","caption":"Floorplan 1"}],"brochures":[{"url":"https://docs.rezi.cloud/2oAC3%2bAqWUT8AsFhu7Pn2mQVoTH7UTLreHjTgGdH3f8%3d/40347887.pdf?v=000000000c524a41","caption":"Brochure 1"}],"epcs":[{"url":"https://media.rightmove.co.uk/8k/7677/144476300/7677_26391003_EPCGRAPH_00_0000.png","caption":"EPC 1"}],"agency":{"url":"https://media.rightmove.co.uk/brand/brand_logo_56245_0006.png","caption":"Country Properties, Hitchin"},"summary":"Sanders Place built in 2005 is a modern development of purpose built apartments located on Walsworth Road and situated within a five minute walk to the train station. This particular apartment is located on the second floor and offers quirky and stylish living accommodation. The property benef...","is_new":false,"zoopla_uprn":10013799885,"zoopla_advert_id":66590241,"zoopla_est":245.0,"zoopla_estimate_date":"2024-03-11T14:48:32.720000Z","zoopla_peak":256.0,"zoopla_peak_date":"Sept 2023","zoopla_rent_estimate":1250.0},{"id":"143290439","channel":"buy","price":250000.0,"date_added":"2024-01-02T12:53:27Z","date_updated":"2024-01-29T09:32:57Z","address_street_num":"66B","address":"Dacre Road, Hitchin","address_postcode":"SG5 1QL","bedrooms":1,"bathrooms":1,"property_group":"Houses","property_group_icon":"🏡","sold_let":"Sold STC","key_features":["Allocated parking space at the front of the property","Council Tax Band: B"],"coordinates":[51.952733,-0.267275],"closest":{"place":"HIT station","miles":0.1,"coords":[51.953323,-0.265135]},"images":[{"url":"https://media.rightmove.co.uk/dir/8k/7677/143290439/7677_26790111_IMG_00_0000_max_656x437.jpeg"},{"url":"https://media.rightmove.co.uk/dir/8k/7677/143290439/7677_26790111_IMG_02_0000_max_656x437.jpeg"},{"url":"https://media.rightmove.co.uk/dir/8k/7677/143290439/7677_26790111_IMG_01_0000_max_656x437.jpeg"},{"url":"https://media.rightmove.co.uk/dir/8k/7677/143290439/7677_26790111_IMG_03_0000_max_656x437.jpeg"},{"url":"https://media.rightmove.co.uk/dir/8k/7677/143290439/7677_26790111_IMG_04_0000_max_656x437.jpeg"},{"url":"https://media.rightmove.co.uk/dir/8k/7677/143290439/7677_26790111_IMG_05_0000_max_656x437.jpeg"},{"url":"https://media.rightmove.co.uk/dir/8k/7677/143290439/7677_26790111_IMG_06_0000_max_656x437.jpeg"},{"url":"https://media.rightmove.co.uk/dir/8k/7677/143290439/7677_26790111_IMG_07_0000_max_656x437.jpeg"}],"floorplans":[{"url":"https://media.rightmove.co.uk/8k/7677/143290439/7677_26790111_FLP_00_0000.jpeg","caption":"Floorplan 1"}],"brochures":[{"url":"https://docs.rezi.cloud/kUL%2fcShOSw4gdI5PMFzl1pC7gMmTtVdB6IOwMY1cK%2fE%3d/39728952.pdf?v=000000000c489749","caption":"Brochure 1"}],"epcs":[{"url":"https://media.rightmove.co.uk/8k/7677/143290439/7677_26790111_EPCGRAPH_00_0000.png","caption":"EPC 1"}],"agency":{"url":"https://media.rightmove.co.uk/brand/brand_logo_56245_0006.png","caption":"Country Properties, Hitchin"},"summary":"This superb property was converted and refurbished back in 2013 to form this unique one bedroom detached property that is ideally located for the train station and local amenities. The ground floor provides an open plan kitchen and living area. The kitchen offers a range of storage c...","is_new":false,"previous_prices":[{"date":"2024-01-28T23:33:58Z","price":260000.0},{"date":"2024-01-29T21:23:57Z","price":250000.0}],"zoopla_uprn":200002765464,"zoopla_advert_id":65748876,"zoopla_est":249.0,"zoopla_estimate_date":"2024-03-11T14:48:32.720000Z","zoopla_peak":499.0,"zoopla_peak_date":"Sept 2023","zoopla_rent_estimate":900.0},{"id":"143876282","channel":"buy","price":225000.0,"date_added":"2024-01-22T11:53:18Z","address_street_num":"86","address":"Walsworth Road, Hitchin","address_postcode":"SG4 9FJ","bedrooms":1,"bathrooms":1,"property_group":"Flats / Apartments","property_group_icon":"🏢","key_features":["Top Floor","Underground Parking","LEASEHOLD","Years left: 109","Ground Rent: 590.0","Service charge: 1500.0","Council Tax Band: B"],"coordinates":[51.95329,-0.26629],"closest":{"place":"HIT station","miles":0.049,"coords":[51.953323,-0.265135]},"images":[{"url":"https://media.rightmove.co.uk/dir/2k/1650/143876282/1650_HIT307012_IMG_14_0000_max_656x437.jpeg"},{"url":"https://media.rightmove.co.uk/dir/2k/1650/143876282/1650_HIT307012_IMG_03_0000_max_656x437.jpeg"},{"url":"https://media.rightmove.co.uk/dir/2k/1650/143876282/1650_HIT307012_IMG_10_0000_max_656x437.jpeg"},{"url":"https://media.rightmove.co.uk/dir/2k/1650/143876282/1650_HIT307012_IMG_07_0000_max_656x437.jpeg"},{"url":"https://media.rightmove.co.uk/dir/2k/1650/143876282/1650_HIT307012_IMG_04_0000_max_656x437.jpeg"},{"url":"https://media.rightmove.co.uk/dir/2k/1650/143876282/1650_HIT307012_IMG_01_0000_max_656x437.jpeg"},{"url":"https://media.rightmove.co.uk/dir/2k/1650/143876282/1650_HIT307012_IMG_02_0000_max_656x437.jpeg"},{"url":"https://media.rightmove.co.uk/dir/2k/1650/143876282/1650_HIT307012_IMG_00_0000_max_656x437.jpeg"},{"url":"https://media.rightmove.co.uk/dir/2k/1650/143876282/1650_HIT307012_IMG_06_0000_max_656x437.jpeg"},{"url":"https://media.rightmove.co.uk/dir/2k/1650/143876282/1650_HIT307012_IMG_11_0000_max_656x437.jpeg"},{"url":"https://media.rightmove.co.uk/dir/2k/1650/143876282/1650_HIT307012_IMG_05_0000_max_656x437.jpeg"},{"url":"https://media.rightmove.co.uk/dir/2k/1650/143876282/1650_HIT307012_IMG_08_0000_max_656x437.jpeg"},{"url":"https://media.rightmove.co.uk/dir/2k/1650/143876282/1650_HIT307012_IMG_09_0000_max_656x437.jpeg"},{"url":"https://media.rightmove.co.uk/dir/2k/1650/143876282/1650_HIT307012_IMG_13_0000_max_656x437.jpeg"},{"url":"https://media.rightmove.co.uk/dir/2k/1650/143876282/1650_HIT307012_IMG_12_0000_max_656x437.jpeg"},{"url":"https://media.rightmove.co.uk/dir/2k/1650/143876282/1650_HIT307012_IMG_15_0000_max_656x437.jpeg"},{"url":"https://media.rightmove.co.uk/dir/2k/1650/143876282/1650_HIT307012_IMG_16_0000_max_656x437.jpeg"}],"floorplans":[{"url":"https://media.rightmove.co.uk/2k/1650/143876282/1650_HIT307012_FLP_00_0000.jpeg","caption":"Floorplan 1"}],"brochures":[{"url":"https://media.rightmove.co.uk/2k/1650/143876282/1650_HIT307012_DOC_01_0001.pdf","caption":"PDF Property Particulars"},{"url":"https://www.connells.co.uk/property/HIT307012","caption":"Full Details"}],"epcs":[{"url":"https://media.rightmove.co.uk/2k/1650/143876282/1650_HIT307012_EPCGRAPH_00_0000.gif","caption":"EPC"}],"agency":{"url":"https://media.rightmove.co.uk/company/clogo_43_0003.jpeg","caption":"Connells, Hitchin"},"summary":"A lovely one double bedroom apartment ideal for a first time buyer. Offering a very large living area, a good size bedroom with cupboard space and luxury bathroom. This property is ideal for a commuter, has underground parking and lovely communal gardens.","is_new":false,"zoopla_uprn":10023319053,"zoopla_advert_id":66456224,"zoopla_est":224.0,"zoopla_estimate_date":"2024-03-11T14:48:32.720000Z","zoopla_peak":254.0,"zoopla_peak_date":"May 2021","zoopla_rent_estimate":1150.0},{"id":"143513966","channel":"buy","price":400000.0,"date_added":"2024-01-10T15:59:03Z","address_street_num":"56","address":"Dacre Road, Hitchin","address_postcode":"SG5 1QL","bedrooms":2,"bathrooms":1,"property_group":"Houses","property_group_icon":"🏡","key_features":["Parking to the rear","Council Tax Band: C"],"coordinates":[51.953295,-0.267741],"closest":{"place":"HIT station","miles":0.111,"coords":[51.953323,-0.265135]},"images":[{"url":"https://media.rightmove.co.uk/dir/8k/7677/143513966/7677_26632668_IMG_00_0000_max_656x437.jpeg"},{"url":"https://media.rightmove.co.uk/dir/8k/7677/143513966/7677_26632668_IMG_01_0000_max_656x437.jpeg"},{"url":"https://media.rightmove.co.uk/dir/8k/7677/143513966/7677_26632668_IMG_02_0000_max_656x437.jpeg"},{"url":"https://media.rightmove.co.uk/dir/8k/7677/143513966/7677_26632668_IMG_03_0000_max_656x437.jpeg"},{"url":"https://media.rightmove.co.uk/dir/8k/7677/143513966/7677_26632668_IMG_04_0000_max_656x437.jpeg"},{"url":"https://media.rightmove.co.uk/dir/8k/7677/143513966/7677_26632668_IMG_05_0000_max_656x437.jpeg"},{"url":"https://media.rightmove.co.uk/dir/8k/7677/143513966/7677_26632668_IMG_06_0000_max_656x437.jpeg"},{"url":"https://media.rightmove.co.uk/dir/8k/7677/143513966/7677_26632668_IMG_07_0000_max_656x437.jpeg"},{"url":"https://media.rightmove.co.uk/dir/8k/7677/143513966/7677_26632668_IMG_08_0000_max_656x437.jpeg"},{"url":"https://media.rightmove.co.uk/dir/8k/7677/143513966/7677_26632668_IMG_09_0000_max_656x437.jpeg"},{"url":"https://media.rightmove.co.uk/dir/8k/7677/143513966/7677_26632668_IMG_10_0000_max_656x437.jpeg"},{"url":"https://media.rightmove.co.uk/dir/8k/7677/143513966/7677_26632668_IMG_11_0000_max_656x437.jpeg"},{"url":"https://media.rightmove.co.uk/dir/8k/7677/143513966/7677_26632668_IMG_12_0000_max_656x437.jpeg"},{"url":"https://media.rightmove.co.uk/dir/8k/7677/143513966/7677_26632668_IMG_13_0000_max_656x437.jpeg"}],"floorplans":[{"url":"https://media.rightmove.co.uk/8k/7677/143513966/7677_26632668_FLP_00_0000.jpeg","caption":"Floorplan 1"}],"brochures":[{"url":"https://docs.rezi.cloud/qrfR%2fiCi3vKr63RW%2fqcDW4LgF863nLC8s9HnLJXpkLQ%3d/39835456.pdf?v=000000000c3567eb","caption":"Brochure 1"}],"epcs":[{"url":"https://media.rightmove.co.uk/8k/7677/143513966/7677_26632668_EPCGRAPH_00_0000.png","caption":"EPC 1"}],"agency":{"url":"https://media.rightmove.co.uk/brand/brand_logo_56245_0006.png","caption":"Country Properties, Hitchin"},"summary":"A charming and well presented two bedroom Victorian terrace property benefitting from parking and set within a sought after location 0.8 miles from Hitchin town centre. This property is offered to the market with no onward chain.To the ground floor is a living room with log burner, sepa...","is_new":false,"zoopla_uprn":100080797184,"zoopla_advert_id":66375272,"zoopla_est":398.0,"zoopla_estimate_date":"2024-03-11T14:48:32.720000Z","zoopla_peak":402.0,"zoopla_peak_date":"Sept 2022","zoopla_rent_estimate":1450.0},{"id":"143350277","channel":"buy","price":250000.0,"date_added":"2024-01-03T18:44:02Z","address_street_num":"43C","address":"Walsworth Road, Hitchin","address_postcode":"SG4 9SU","bedrooms":1,"bathrooms":1,"property_group":"Flats / Apartments","property_group_icon":"🏢","sold_let":"Sold STC","key_features":["Permit parking available nearby","LEASEHOLD","Years left: 150","Ground Rent: 75.0","Service charge: 500.0"],"coordinates":[51.951674,-0.268346],"closest":{"place":"HIT station","miles":0.178,"coords":[51.953323,-0.265135]},"images":[{"url":"https://media.rightmove.co.uk/dir/9k/8567/143350277/8567_HIT230214_IMG_03_0000_max_656x437.jpeg","caption":"Picture No. 05"},{"url":"https://media.rightmove.co.uk/dir/9k/8567/143350277/8567_HIT230214_IMG_00_0000_max_656x437.jpeg","caption":"Picture No. 15"},{"url":"https://media.rightmove.co.uk/dir/9k/8567/143350277/8567_HIT230214_IMG_01_0000_max_656x437.jpeg","caption":"Picture No. 03"},{"url":"https://media.rightmove.co.uk/dir/9k/8567/143350277/8567_HIT230214_IMG_02_0000_max_656x437.jpeg","caption":"Picture No. 04"},{"url":"https://media.rightmove.co.uk/dir/9k/8567/143350277/8567_HIT230214_IMG_04_0000_max_656x437.jpeg","caption":"Picture No. 06"},{"url":"https://media.rightmove.co.uk/dir/9k/8567/143350277/8567_HIT230214_IMG_05_0000_max_656x437.jpeg","caption":"Picture No. 11"},{"url":"https://media.rightmove.co.uk/dir/9k/8567/143350277/8567_HIT230214_IMG_06_0000_max_656x437.jpeg","caption":"Picture No. 12"},{"url":"https://media.rightmove.co.uk/dir/9k/8567/143350277/8567_HIT230214_IMG_07_0000_max_656x437.jpeg","caption":"Picture No. 13"},{"url":"https://media.rightmove.co.uk/dir/9k/8567/143350277/8567_HIT230214_IMG_08_0000_max_656x437.jpeg","caption":"Picture No. 08"},{"url":"https://media.rightmove.co.uk/dir/9k/8567/143350277/8567_HIT230214_IMG_09_0000_max_656x437.jpeg","caption":"Picture No. 09"},{"url":"https://media.rightmove.co.uk/dir/9k/8567/143350277/8567_HIT230214_IMG_10_0000_max_656x437.jpeg","caption":"Picture No. 07"},{"url":"https://media.rightmove.co.uk/dir/9k/8567/143350277/8567_HIT230214_IMG_11_0000_max_656x437.jpeg","caption":"Picture No. 14"}],"floorplans":[{"url":"https://media.rightmove.co.uk/9k/8567/143350277/8567_HIT230214_FLP_00_0000.jpeg","caption":"Picture No. 02"}],"brochures":[{"url":"https://www.your-move.co.uk/property/HIT230214","caption":"Web Details"}],"epcs":[{"url":"https://media.rightmove.co.uk/9k/8567/143350277/8567_HIT230214_EPCGRAPH_00_0000.png","caption":"EPC Rating Graph"}],"agency":{"url":"https://media.rightmove.co.uk/brand/brand_logo_92276_0000.jpeg","caption":"Your Move, Hitchin"},"summary":"Introducing this charming one-bedroom flat located in a sought-after area within Hitchin. Situated within a split-level period property, this home is in good condition and offers a warm and inviting ambiance. The property is a one of a kind and is ideal for couples seeking a comfortable, stylish ...","is_new":false,"zoopla_uprn":100080807620,"zoopla_advert_id":66326833,"zoopla_est":249.0,"zoopla_estimate_date":"2024-03-11T14:48:32.720000Z","zoopla_peak":249.0,"zoopla_peak_date":"Feb 2024","zoopla_rent_estimate":1250.0},{"id":"136480994","channel":"buy","price":280000.0,"date_added":"2023-06-23T12:29:49+01:00","date_updated":"2023-12-26T05:27:12Z","address_street_num":"58","address":"Walsworth Road, Hitchin","address_postcode":"SG4 9FJ","bedrooms":2,"bathrooms":2,"size_sqm":67.0,"property_group":"Flats / Apartments","property_group_icon":"🏢","sold_let":"Sold STC","key_features":["Underground Parking","LEASEHOLD","Years left: 109","Ground Rent: 350.0","Service charge: 1854.32","Council Tax Band: C"],"coordinates":[51.95329,-0.26629],"closest":{"place":"HIT station","miles":0.049,"coords":[51.953323,-0.265135]},"images":[{"url":"https://media.rightmove.co.uk/dir/2k/1650/136480994/1650_HIT307217_IMG_12_0000_max_656x437.jpeg"},{"url":"https://media.rightmove.co.uk/dir/2k/1650/136480994/1650_HIT307217_IMG_07_0000_max_656x437.jpeg"},{"url":"https://media.rightmove.co.uk/dir/2k/1650/136480994/1650_HIT307217_IMG_03_0000_max_656x437.jpeg"},{"url":"https://media.rightmove.co.uk/dir/2k/1650/136480994/1650_HIT307217_IMG_11_0000_max_656x437.jpeg"},{"url":"https://media.rightmove.co.uk/dir/2k/1650/136480994/1650_HIT307217_IMG_10_0000_max_656x437.jpeg"},{"url":"https://media.rightmove.co.uk/dir/2k/1650/136480994/1650_HIT307217_IMG_09_0000_max_656x437.jpeg"},{"url":"https://media.rightmove.co.uk/dir/2k/1650/136480994/1650_HIT307217_IMG_13_0000_max_656x437.jpeg"},{"url":"https://media.rightmove.co.uk/dir/2k/1650/136480994/1650_HIT307217_IMG_08_0000_max_656x437.jpeg"},{"url":"https://media.rightmove.co.uk/dir/2k/1650/136480994/1650_HIT307217_IMG_05_0000_max_656x437.jpeg"},{"url":"https://media.rightmove.co.uk/dir/2k/1650/136480994/1650_HIT307217_IMG_06_0000_max_656x437.jpeg"},{"url":"https://media.rightmove.co.uk/dir/2k/1650/136480994/1650_HIT307217_IMG_04_0000_max_656x437.jpeg"},{"url":"https://media.rightmove.co.uk/dir/2k/1650/136480994/1650_HIT307217_IMG_01_0000_max_656x437.jpeg"},{"url":"https://media.rightmove.co.uk/dir/2k/1650/136480994/1650_HIT307217_IMG_00_0000_max_656x437.jpeg"},{"url":"https://media.rightmove.co.uk/dir/2k/1650/136480994/1650_HIT307217_IMG_14_0000_max_656x437.jpeg"},{"url":"https://media.rightmove.co.uk/dir/2k/1650/136480994/1650_HIT307217_IMG_02_0000_max_656x437.jpeg"}],"floorplans":[{"url":"https://media.rightmove.co.uk/2k/1650/136480994/1650_HIT307217_FLP_00_0000.jpeg","caption":"Floorplan 1"}],"brochures":[{"url":"https://www.connells.co.uk/property/HIT307217","caption":"Full Details"}],"epcs":[{"url":"https://media.rightmove.co.uk/2k/1650/136480994/1650_HIT307217_EPCGRAPH_00_0000.gif","caption":"EPC"}],"agency":{"url":"https://media.rightmove.co.uk/company/clogo_43_0003.jpeg","caption":"Connells, Hitchin"},"summary":"A stunning two bedroom apartment offering direct access to the gardens, underground parking and two bathrooms. Johnson Place is a popular central development offering excellent access to the train station and the town centre.","is_new":false,"previous_prices":[{"date":"2023-09-21T11:50:04+01:00","price":300000.0},{"date":"2023-10-05T15:57:26+01:00","price":290000.0},{"date":"2023-12-25T15:00:22Z","price":290000.0},{"date":"2023-12-29T01:57:43Z","price":280000.0}],"zoopla_uprn":10023319025,"zoopla_advert_id":64953254,"zoopla_est":278.0,"zoopla_estimate_date":"2024-03-11T14:48:32.720000Z","zoopla_peak":303.0,"zoopla_peak_date":"Dec 2022","zoopla_rent_estimate":1400.0},{"id":"143169656","channel":"buy","price":325000.0,"date_added":"2023-12-26T01:30:05Z","address_street_num":"5 The Foundry","address":"Cooks Way, Hitchin","address_postcode":"SG4 0BW","bedrooms":2,"bathrooms":2,"property_group":"Flats / Apartments","property_group_icon":"🏢","sold_let":"Sold STC","key_features":["Ground floor Apartment","Allocated parking (plus visitors bays)","LEASEHOLD","Ground Rent: 250.0","Service charge: 1800.0","Council Tax Band: C"],"coordinates":[51.95641,-0.26442],"closest":{"place":"HIT station","miles":0.216,"coords":[51.953323,-0.265135]},"images":[{"url":"https://media.rightmove.co.uk/dir/1k/436/143169656/436_BHI230277_IMG_00_0000_max_656x437.jpeg","caption":"Rear View"},{"url":"https://media.rightmove.co.uk/dir/1k/436/143169656/436_BHI230277_IMG_01_0000_max_656x437.jpeg","caption":"Living/Dining Area"},{"url":"https://media.rightmove.co.uk/dir/1k/436/143169656/436_BHI230277_IMG_02_0000_max_656x437.jpeg","caption":"Living Room"},{"url":"https://media.rightmove.co.uk/dir/1k/436/143169656/436_BHI230277_IMG_03_0000_max_656x437.jpeg","caption":"Living Room"},{"url":"https://media.rightmove.co.uk/dir/1k/436/143169656/436_BHI230277_IMG_04_0000_max_656x437.jpeg","caption":"Dining Area"},{"url":"https://media.rightmove.co.uk/dir/1k/436/143169656/436_BHI230277_IMG_05_0000_max_656x437.jpeg","caption":"Kitchen"},{"url":"https://media.rightmove.co.uk/dir/1k/436/143169656/436_BHI230277_IMG_06_0000_max_656x437.jpeg","caption":"Bedroom One"},{"url":"https://media.rightmove.co.uk/dir/1k/436/143169656/436_BHI230277_IMG_07_0000_max_656x437.jpeg","caption":"Bedroom One"},{"url":"https://media.rightmove.co.uk/dir/1k/436/143169656/436_BHI230277_IMG_08_0000_max_656x437.jpeg","caption":"En-Suite"},{"url":"https://media.rightmove.co.uk/dir/1k/436/143169656/436_BHI230277_IMG_09_0000_max_656x437.jpeg","caption":"Bedroom Two"},{"url":"https://media.rightmove.co.uk/dir/1k/436/143169656/436_BHI230277_IMG_10_0000_max_656x437.jpeg","caption":"Bathroom"},{"url":"https://media.rightmove.co.uk/dir/1k/436/143169656/436_BHI230277_IMG_11_0000_max_656x437.jpeg","caption":"Entrance Hallway"},{"url":"https://media.rightmove.co.uk/dir/1k/436/143169656/436_BHI230277_IMG_12_0000_max_656x437.jpeg","caption":"Communal Garden"},{"url":"https://media.rightmove.co.uk/dir/1k/436/143169656/436_BHI230277_IMG_13_0000_max_656x437.jpeg","caption":"Front"},{"url":"https://media.rightmove.co.uk/dir/1k/436/143169656/436_BHI230277_IMG_14_0000_max_656x437.jpeg","caption":"Allocated Parking"}],"floorplans":[{"url":"https://media.rightmove.co.uk/1k/436/143169656/436_BHI230277_FLP_00_0000.jpeg","caption":"FLOOR-PLAN"}],"epcs":[{"url":"https://media.rightmove.co.uk/1k/436/143169656/436_BHI230277_EPCGRAPH_00_0000.png","caption":"EPC Rating Graph"}],"agency":{"url":"https://media.rightmove.co.uk/brand/brand_logo_25_0004.png","caption":"Taylors Estate Agents, Hitchin"},"summary":"A pleasure to offer for sale this stunning two bedroom ground floor apartment on The Foundry which was used as the show home when the development was built in 2018 and occupies a dual aspect corner plot overlooking the communal Gardens. This beautifully presented home comprises of a sp...","is_new":false,"zoopla_uprn":10023329433,"zoopla_advert_id":66289816,"zoopla_est":321.0,"zoopla_estimate_date":"2024-03-11T14:48:32.720000Z","zoopla_peak":350.0,"zoopla_peak_date":"Jul 2022","zoopla_rent_estimate":1600.0},{"id":"145123901","channel":"buy","price":250000.0,"date_added":"2023-12-07T14:30:37Z","address":"Johnson Place, Walsworth Road, Hitchin","address_postcode":"SG4 9FJ","bedrooms":2,"bathrooms":2,"size_sqm":60.3,"property_group":"Flats / Apartments","property_group_icon":"🏢","sold_let":"Sold STC","key_features":["LEASEHOLD","Years left: 115","Ground Rent: 700.0","Service charge: 1854.32","Council Tax Band: C"],"coordinates":[51.95333,-0.266389],"closest":{"place":"HIT station","miles":0.054,"coords":[51.953323,-0.265135]},"images":[{"url":"https://media.rightmove.co.uk/dir/118k/117970/145123901/117970_32392038_IMG_00_0000_max_656x437.jpeg","caption":"DSC_0009.JPG"},{"url":"https://media.rightmove.co.uk/dir/118k/117970/145123901/117970_32392038_IMG_01_0000_max_656x437.jpeg","caption":"DSC_0010.JPG"},{"url":"https://media.rightmove.co.uk/dir/118k/117970/145123901/117970_32392038_IMG_02_0000_max_656x437.jpeg","caption":"DSC_0018.JPG"},{"url":"https://media.rightmove.co.uk/dir/118k/117970/145123901/117970_32392038_IMG_03_0000_max_656x437.jpeg","caption":"Living/Kitchen Area"},{"url":"https://media.rightmove.co.uk/dir/118k/117970/145123901/117970_32392038_IMG_04_0000_max_656x437.jpeg","caption":"DSC_0013.JPG"},{"url":"https://media.rightmove.co.uk/dir/118k/117970/145123901/117970_32392038_IMG_05_0000_max_656x437.jpeg","caption":"DSC_0014.JPG"},{"url":"https://media.rightmove.co.uk/dir/118k/117970/145123901/117970_32392038_IMG_06_0000_max_656x437.jpeg","caption":"DSC_0019.JPG"},{"url":"https://media.rightmove.co.uk/dir/118k/117970/145123901/117970_32392038_IMG_07_0000_max_656x437.jpeg","caption":"Entrance Hall"},{"url":"https://media.rightmove.co.uk/dir/118k/117970/145123901/117970_32392038_IMG_08_0000_max_656x437.jpeg","caption":"DSC_0006.JPG"},{"url":"https://media.rightmove.co.uk/dir/118k/117970/145123901/117970_32392038_IMG_09_0000_max_656x437.jpeg","caption":"DSC_0004.JPG"},{"url":"https://media.rightmove.co.uk/dir/118k/117970/145123901/117970_32392038_IMG_10_0000_max_656x437.jpeg","caption":"DSC_0007.JPG"},{"url":"https://media.rightmove.co.uk/dir/118k/117970/145123901/117970_32392038_IMG_11_0000_max_656x437.jpeg","caption":"DSC_0002.JPG"},{"url":"https://media.rightmove.co.uk/dir/118k/117970/145123901/117970_32392038_IMG_12_0000_max_656x437.jpeg","caption":"DSC_0001.JPG"},{"url":"https://media.rightmove.co.uk/dir/118k/117970/145123901/117970_32392038_IMG_13_0000_max_656x437.jpeg","caption":"DSC_0043.JPG"},{"url":"https://media.rightmove.co.uk/dir/118k/117970/145123901/117970_32392038_IMG_14_0000_max_656x437.jpeg","caption":"OUTSIDE"},{"url":"https://media.rightmove.co.uk/dir/118k/117970/145123901/117970_32392038_IMG_15_0000_max_656x437.jpeg","caption":"DSC_0946.JPG"}],"floorplans":[{"url":"https://media.rightmove.co.uk/118k/117970/145123901/117970_32392038_FLP_00_0000.jpeg","caption":"Johnson Place.jpg"}],"brochures":[{"url":"https://media.rightmove.co.uk/118k/117970/145123901/117970_32392038_DOC_02_0000.pdf","caption":"Main"},{"url":"https://www.vebra.com/details/property/32392038","caption":"Brochure"}],"epcs":[{"url":"https://media.rightmove.co.uk/118k/117970/145123901/117970_32392038_EPCGRAPH_00_0000.png","caption":"EE Rating"},{"url":"https://media.rightmove.co.uk/118k/117970/145123901/117970_32392038_EPCGRAPH_01_0000.png","caption":"EI Rating"}],"agency":{"url":"https://media.rightmove.co.uk/brand/brand_logo_94565_0000.png","caption":"Belvoir, Hitchin"},"summary":"LOTS OF NATURAL LIGHT IN THIS SPACIOUS APARTMENT - Belvoir are delighted to market this second floor apartment situated close to the mainline station and within easy access to the town centre. The accommodation comprises open plan living and kitchen space with Juliette balcony and lots of natura...","is_new":false}],"favicon":"favicon_johnsonplace.ico"}